django_hosts/__init__.py
django_hosts/apps.py
django_hosts/callbacks.py
django_hosts/checks.py
django_hosts/defaults.py
django_hosts/managers.py
django_hosts/middleware.py
django_hosts/resolvers.py
django_hosts/utils.py
django_hosts/templatetags/__init__.py
django_hosts/templatetags/hosts.py
django_hosts/templatetags/hosts_override.py
tests/__init__.py
tests/base.py
tests/broken_module.py
tests/models.py
tests/settings.py
tests/test_defaults.py
tests/test_middleware.py
tests/test_resolvers.py
tests/test_sites.py
tests/test_templatetags.py
tests/test_utils.py
tests/views.py
tests/hosts/__init__.py
tests/hosts/appended.py
tests/hosts/blank.py
tests/hosts/multiple.py
tests/hosts/simple.py
tests/migrations/0001_initial.py
tests/migrations/__init__.py
tests/urls/__init__.py
tests/urls/complex.py
tests/urls/multiple.py
tests/urls/root.py
tests/urls/simple.py
django_hosts-5.0.dist-info/AUTHORS
django_hosts-5.0.dist-info/LICENSE
django_hosts-5.0.dist-info/METADATA
django_hosts-5.0.dist-info/WHEEL
django_hosts-5.0.dist-info/top_level.txt
django_hosts-5.0.dist-info/RECORD
